gscrew/__init__.py
gscrew/geometric_algebra.py
gscrew/screw.py
gscrew-1.1.0.dist-info/LICENSE
gscrew-1.1.0.dist-info/METADATA
gscrew-1.1.0.dist-info/WHEEL
gscrew-1.1.0.dist-info/top_level.txt
gscrew-1.1.0.dist-info/RECORD
