Metadata-Version: 2.2
Name: gscrew
Version: 1.1.0
Summary: A Python module to manipulate generalized Screws and Coscrews in Geometric Algebra (real Clifford algebra).
Author: Antoine Royer, Loris Delafosse
Project-URL: Homepage, https://github.com/GenScrew/GScrew
Project-URL: Documentation, http://gscrew.readthedocs.io/
Classifier: Programming Language :: Python :: 3
Classifier: License :: OSI Approved :: GNU General Public License v3 or later (GPLv3+)
Classifier: Development Status :: 4 - Beta
Requires-Python: >=3.7
License-File: LICENSE
Requires-Dist: numpy>=1.24
Provides-Extra: doc
Requires-Dist: sphinx>=7.0.1; extra == "doc"
Requires-Dist: sphinx-rtd-theme; extra == "doc"
Requires-Dist: sphinx-autodocgen; extra == "doc"
